scraperouter/__init__.py
scraperouter-0.0.0.dist-info/licenses/LICENSE
scraperouter-0.0.0.dist-info/METADATA
scraperouter-0.0.0.dist-info/WHEEL
scraperouter-0.0.0.dist-info/top_level.txt
scraperouter-0.0.0.dist-info/RECORD
